Metadata-Version: 2.1
Name: nonebot-plugin-BingImage
Version: 0.0.1
Summary: Get Bing Images for NoneBot2
Home-page: https://github.com/ericzhang-debug/nonebot_plugin_BingImage
Author: EricZhang
Author-email: 15364519511@163.com
License: GPLv3 Licence
Keywords: nonebot,nonebot-plugin,BingImage,Bing,nonebot-plugin-BingImage
Platform: any
License-File: LICENSE
Requires-Dist: nonebot2 (>=2.0.0b3)
Requires-Dist: httpx (<1.0.0,>=0.20.0)
Requires-Dist: nonebot-adapter-onebot (>=2.0.0b1)
Requires-Dist: nonebot-plugin-apscheduler (>=0.1.0)
Requires-Dist: requests
Requires-Dist: parsel
Requires-Dist: faker
